django_meilisearch_indexer/__init__.py
django_meilisearch_indexer/indexers.py
django_meilisearch_indexer/serializers.py
django_meilisearch_indexer/types.py
django_meilisearch_indexer-1.0.3.dist-info/licenses/LICENSE
django_meilisearch_indexer-1.0.3.dist-info/METADATA
django_meilisearch_indexer-1.0.3.dist-info/WHEEL
django_meilisearch_indexer-1.0.3.dist-info/top_level.txt
django_meilisearch_indexer-1.0.3.dist-info/RECORD
