Metadata-Version: 2.4
Name: django_meilisearch_indexer
Version: 1.0.3
Summary: Meilisearch indexer for django models and related utilities
Author-email: Jordan Kowal <kowaljordan@gmail.com>
Maintainer-email: Jordan Kowal <kowaljordan@gmail.com>
License: MIT License
Project-URL: Changelog, https://github.com/Jordan-Kowal/django-meilisearch-indexer/blob/main/CHANGELOG.md
Project-URL: Issues, https://github.com/Jordan-Kowal/django-meilisearch-indexer/issues
Project-URL: Release notes, https://github.com/Jordan-Kowal/django-meilisearch-indexer/releases
Project-URL: Source, https://github.com/Jordan-Kowal/django-meilisearch-indexer
Keywords: django,meilisearch,indexer
Classifier: Development Status :: 5 - Production/Stable
Classifier: Intended Audience :: Developers
Classifier: License :: OSI Approved :: MIT License
Classifier: Operating System :: Microsoft :: Windows
Classifier: Operating System :: POSIX
Classifier: Operating System :: Unix
Classifier: Operating System :: MacOS
Classifier: Programming Language :: Python
Classifier: Programming Language :: Python :: 3
Classifier: Programming Language :: Python :: 3.9
Classifier: Programming Language :: Python :: 3.10
Classifier: Programming Language :: Python :: 3.11
Classifier: Programming Language :: Python :: 3.12
Classifier: Programming Language :: Python :: 3.13
Classifier: Programming Language :: Python :: Implementation :: CPython
Classifier: Topic :: Software Development
Requires-Python: >=3.9
License-File: LICENSE
Requires-Dist: django>=4.0.0
Requires-Dist: djangorestframework>=3.13.0
Requires-Dist: meilisearch>=0.28.0
Requires-Dist: typing-extensions>=4.12.2
Dynamic: license-file
